star/__init__.py
star/__main__.py
star/cli.py
star/version.py
python_star-0.1.1.dist-info/LICENCE
python_star-0.1.1.dist-info/METADATA
python_star-0.1.1.dist-info/WHEEL
python_star-0.1.1.dist-info/entry_points.txt
python_star-0.1.1.dist-info/top_level.txt
python_star-0.1.1.dist-info/RECORD
