Metadata-Version: 2.1
Name: python-star
Version: 0.1.1
Summary: A command-line tool for simplifying project setup and development tasks.
Home-page: https://github.com/sikandar1838/star
Author: Sikandar Moyal
Author-email: sikandar1838@gmail.com
License: MIT
Keywords: CLI,project setup,testing,development,automation,scripting,workflow,convenience,productivity,deployment,utility,developer tool,single command
Classifier: Programming Language :: Python :: 3
Classifier: License :: OSI Approved :: MIT License
Classifier: Operating System :: OS Independent
License-File: LICENCE
Requires-Dist: console-py ==0.1.3
